pyipx800/__init__.py
pyipx800-0.0.2.dist-info/LICENSE
pyipx800-0.0.2.dist-info/METADATA
pyipx800-0.0.2.dist-info/WHEEL
pyipx800-0.0.2.dist-info/top_level.txt
pyipx800-0.0.2.dist-info/RECORD
