Metadata-Version: 2.1
Name: pyipx800
Version: 0.0.2
Summary: Package to control IPX800v4 from GCEElectronics
Home-page: https://github.com/slashx57/pyipx800
Author: slashx57
Author-email: boiselet@free.fr
License: UNKNOWN
Platform: UNKNOWN
Classifier: Programming Language :: Python :: 3
Classifier: License :: OSI Approved :: MIT License
Classifier: Operating System :: OS Independent
Requires-Python: >=3.6
